alivebot/__init__.py
alivebot/alivebot.py
alivebot-0.1.22.dist-info/LICENSE
alivebot-0.1.22.dist-info/METADATA
alivebot-0.1.22.dist-info/WHEEL
alivebot-0.1.22.dist-info/top_level.txt
alivebot-0.1.22.dist-info/RECORD
