Metadata-Version: 2.1
Name: alivebot
Version: 0.1.22
Summary: A script to find and react to ALIVE commands in comments
Home-page: https://github.com/flaxz/alivebot
Author: Erik Gustafsson and Hive Pizza Team
Author-email: erikegse@gmail.com
Project-URL: Bug Tracker, https://github.com/flaxz/alivebot/issues
Classifier: Programming Language :: Python :: 3
Classifier: License :: OSI Approved :: MIT License
Classifier: Operating System :: OS Independent
Requires-Python: >=3.6
License-File: LICENSE
